supertemplater/__init__.py
supertemplater/builders/__init__.py
supertemplater/builders/logger_builder.py
supertemplater/cli.py
supertemplater/constants.py
supertemplater/context.py
supertemplater/exceptions.py
supertemplater/git_repository.py
supertemplater/github_repository.py
supertemplater/merge_strategies.py
supertemplater/models/__init__.py
supertemplater/models/base.py
supertemplater/models/directory_dependency.py
supertemplater/models/file_dependency.py
supertemplater/models/git_dependency.py
supertemplater/models/github_dependency.py
supertemplater/models/log_level.py
supertemplater/models/project.py
supertemplater/models/project_variables.py
supertemplater/preloaded_resolver.py
supertemplater/prompt_resolver.py
supertemplater/protocols/__init__.py
supertemplater/protocols/basic_resolver.py
supertemplater/protocols/choices_resolver.py
supertemplater/protocols/dependency.py
supertemplater/protocols/merge_strategy.py
supertemplater/protocols/mergeable.py
supertemplater/protocols/renderable.py
supertemplater/protocols/repository_provider.py
supertemplater/protocols/secrets_resolver.py
supertemplater/protocols/variable_resolver.py
supertemplater/settings/__init__.py
supertemplater/settings/cache_settings.py
supertemplater/settings/jinja_settings.py
supertemplater/settings/logging_settings.py
supertemplater/settings/project_settings.py
supertemplater/settings/settings.py
supertemplater/settings/sources.py
supertemplater/utils.py
supertemplater-1.8.0.dist-info/LICENSE
supertemplater-1.8.0.dist-info/METADATA
supertemplater-1.8.0.dist-info/WHEEL
supertemplater-1.8.0.dist-info/entry_points.txt
supertemplater-1.8.0.dist-info/RECORD
